<annotation verified="yes">
    <folder>Annotation</folder>
    <filename>0-10_C0370.mp4#t=0.95.jpg</filename>
    <path>items-PascalVOC-export/Annotations/0-10_C0370.mp4#t=0.95.jpg</path>
    <source>
        <database>Unknown</database>
    </source>
    <size>
        <width>1920</width>
        <height>1080</height>
        <depth>3</depth>
    </size>
    <segmented>0</segmented>
    <object>
    <name>BISCO_CafeAuLet</name>
    <pose>Unspecified</pose>
    <truncated>0</truncated>
    <difficult>0</difficult>
    <bndbox>
        <xmin>523.1348684210526</xmin>
        <ymin>282.1282894736842</ymin>
        <xmax>730.6924342105262</xmax>
        <ymax>625.125</ymax>
    </bndbox>
</object><object>
    <name>BISCO_CafeAuLet</name>
    <pose>Unspecified</pose>
    <truncated>0</truncated>
    <difficult>0</difficult>
    <bndbox>
        <xmin>895.0460526315788</xmin>
        <ymin>229.8108552631579</ymin>
        <xmax>1143.9424342105262</xmax>
        <ymax>558.1825657894736</ymax>
    </bndbox>
</object>
</annotation>
